LensMotionMania/__init__.py
LensMotionMania/dependencies.py
LensMotionMania/display.py
LensMotionMania/filters.py
LensMotionMania/io.py
LensMotionMania/noises.py
LensMotionMania/report.py
LensMotionMania/Utils/__init__.py
LensMotionMania/Utils/check.py
LensMotionMania/Utils/color.py
LensMotionMania/Utils/transform.py
LensMotionMania-0.1.dist-info/LICENSE
LensMotionMania-0.1.dist-info/METADATA
LensMotionMania-0.1.dist-info/WHEEL
LensMotionMania-0.1.dist-info/top_level.txt
LensMotionMania-0.1.dist-info/RECORD
